cgal_pybind/__init__.py
cgal_pybind/version.py
cgal_pybind/_cgal_pybind.cpython-310-x86_64-linux-gnu.so
cgal_pybind.libs/libgmp-afec2dd4.so.10.2.0
cgal_pybind.libs/libmpfr-54b13606.so.4.1.1
cgal_pybind-0.1.6.dist-info/AUTHORS.txt
cgal_pybind-0.1.6.dist-info/METADATA
cgal_pybind-0.1.6.dist-info/RECORD
cgal_pybind-0.1.6.dist-info/top_level.txt
cgal_pybind-0.1.6.dist-info/LICENSE.txt
cgal_pybind-0.1.6.dist-info/WHEEL
