Metadata-Version: 2.1
Name: cgal-pybind
Version: 0.1.6
Summary: Python bindings for some CGAL classes
Author: Blue Brain Project, EPFL
Project-URL: Homepage, https://github.com/BlueBrain/cgal-pybind
Project-URL: Repository, https://github.com/BlueBrain/cgal-pybind
Project-URL: Issues, https://github.com/BlueBrain/cgal-pybind/issues
Project-URL: Tracker, https://github.com/BlueBrain/cgal-pybind/issues
Classifier: Development Status :: 2 - Pre-Alpha
Classifier: Programming Language :: Python
Classifier: Programming Language :: Python :: 3
Classifier: Programming Language :: Python :: 3.8
Classifier: Programming Language :: Python :: 3.9
Classifier: Programming Language :: Python :: 3.10
Classifier: Programming Language :: Python :: 3.11
Classifier: Programming Language :: Python :: 3.12
Requires-Python: >=3.8
License-File: LICENSE.txt
License-File: AUTHORS.txt
Requires-Dist: numpy>=1.14.5
Provides-Extra: tests
Requires-Dist: trimesh>=2.38.10; extra == "tests"
Requires-Dist: pytest; extra == "tests"
